MANIFEST.in
README.rst
VERSION
setup.cfg
setup.py
docs/api.rst
docs/conf.py
docs/index.rst
docs/storage.rst
uriutils/__init__.py
uriutils/storages.py
uriutils/uriutils.py
uriutils.egg-info/PKG-INFO
uriutils.egg-info/SOURCES.txt
uriutils.egg-info/dependency_links.txt
uriutils.egg-info/top_level.txt
uriutils.egg-info/zip-safe